cordova/__init__.py
cordova/index.js
cordova/templates/config.xml
cordova/templates/head.html
cordova/templates/package.json
mkdocs_cordova_plugin-0.0.1.dist-info/DESCRIPTION.rst
mkdocs_cordova_plugin-0.0.1.dist-info/METADATA
mkdocs_cordova_plugin-0.0.1.dist-info/RECORD
mkdocs_cordova_plugin-0.0.1.dist-info/WHEEL
mkdocs_cordova_plugin-0.0.1.dist-info/entry_points.txt
mkdocs_cordova_plugin-0.0.1.dist-info/metadata.json
mkdocs_cordova_plugin-0.0.1.dist-info/top_level.txt
