Metadata-Version: 2.0
Name: mkdocs-cordova-plugin
Version: 0.0.1
Summary: Deploy documentation to any mobile device via Apache Cordova
Home-page: https://gitlab.com/lramage94/mkdocs-cordova-plugin
Author: Lucas Ramage
Author-email: ramage.lucas@protonmail.com
License: MIT
Keywords: mkdocs python markdown cordova apache mobile
Platform: UNKNOWN
Classifier: Intended Audience :: Developers
Classifier: Intended Audience :: Information Technology
Classifier: License :: OSI Approved :: MIT License
Classifier: Programming Language :: Python
Requires-Dist: mkdocs (>=0.17)
